LICENSE
MANIFEST.in
README.rst
setup.py
sugarcrm.py
sugarcrm.egg-info/PKG-INFO
sugarcrm.egg-info/SOURCES.txt
sugarcrm.egg-info/dependency_links.txt
sugarcrm.egg-info/requires.txt
sugarcrm.egg-info/top_level.txt